urn_citation/__init__.py
urn_citation/cite2urn.py
urn_citation/ctsurn.py
urn_citation/urn.py
urn_citation-0.7.2.dist-info/METADATA
urn_citation-0.7.2.dist-info/WHEEL
urn_citation-0.7.2.dist-info/licenses/LICENSE
urn_citation-0.7.2.dist-info/RECORD
