Metadata-Version: 2.4
Name: urn-citation
Version: 0.7.2
Summary: A Python library for working with CITE architecture URNs for scholarly citation.
License-File: LICENSE
Requires-Python: >=3.14
Requires-Dist: ipython
Requires-Dist: pydantic>=2.12.5
